Workbook

Sheet Assumptions
A1: Case: Renting Out One Apartment — Assumptions
A3: Item | B3: Value
A4: Apartment value | B4: 13000000
A5: Furniture, appliances, and other property | B5: 3600000
A6: Initial renovation cost | B6: 2400000
A7: Monthly depreciation of renovation + furniture/appliances (20 years to zero) | B7: =(B5+B6)/(20*12) -> 25000
A8: Mortgage debt at the beginning of January | B8: 10000000
A9: Monthly mortgage principal repayment (49,000 payment minus interest) | B9: =49000-B10 -> 34000
A10: Monthly mortgage interest | B10: 15000
A11: Cash balance at the beginning of January | B11: 200000
A12: Monthly rent | B12: 80000
A13: Income tax rate | B13: 0.13
A16: All amounts are in rubles. Yellow cells are assumptions used by formulas in the statements. Renovation and furniture/appliances depreciate to zero over 20 full years. Monthly mortgage cash payment is 49,000: interest plus principal repayment.

Sheet P&L
A1: Profit & Loss Statement
A2: Monthly view, accrual basis
A4: P&L item | B4: January | C4: February | D4: March
A5: Rental revenue | B5: =Assumptions!$B$12 -> 80000 | C5: =Assumptions!$B$12 -> 80000 | D5: =Assumptions!$B$12 -> 80000
A6: Utilities paid by owner | B6: -6000 | C6: -6500 | D6: -6000
A7: Maintenance and repairs | B7: -5000 | C7: -15000 | D7: -7000
A8: Mortgage interest | B8: =-Assumptions!$B$10 -> -15000 | C8: =-Assumptions!$B$10 -> -15000 | D8: =-Assumptions!$B$10 -> -15000
A9: Depreciation of renovation + furniture/appliances | B9: =-Assumptions!$B$7 -> -25000 | C9: =-Assumptions!$B$7 -> -25000 | D9: =-Assumptions!$B$7 -> -25000
A10: Profit before tax | B10: =SUM(B5:B9) -> 29000 | C10: =SUM(C5:C9) -> 18500 | D10: =SUM(D5:D9) -> 27000
A11: Income tax | B11: =-MAX(0,B10*Assumptions!$B$13) -> -3770 | C11: =-MAX(0,C10*Assumptions!$B$13) -> -2405 | D11: =-MAX(0,D10*Assumptions!$B$13) -> -3510
A12: Net profit | B12: =B10+B11 -> 25230 | C12: =C10+C11 -> 16095 | D12: =D10+D11 -> 23490
A14: Teaching note: tax reduces accounting profit in P&L and is also a real cash outflow in Cash Flow. Depreciation reduces profit but does not create cash outflow in the month.

Sheet Balance Sheet
A1: Balance Sheet
A2: Position at the end of each month
A4: Balance Sheet item | B4: End of January | C4: End of February | D4: End of March
A5: Apartment | B5: =Assumptions!$B$4 -> 13000000 | C5: =Assumptions!$B$4 -> 13000000 | D5: =Assumptions!$B$4 -> 13000000
A6: Furniture, appliances, and other property, net book value | B6: =Assumptions!$B$5-Assumptions!$B$5/(20*12) -> 3585000 | C6: =Assumptions!$B$5-Assumptions!$B$5/(20*12)*2 -> 3570000 | D6: =Assumptions!$B$5-Assumptions!$B$5/(20*12)*3 -> 3555000
A7: Renovation, net book value | B7: =Assumptions!$B$6-Assumptions!$B$6/(20*12) -> 2390000 | C7: =Assumptions!$B$6-Assumptions!$B$6/(20*12)*2 -> 2380000 | D7: =Assumptions!$B$6-Assumptions!$B$6/(20*12)*3 -> 2370000
A8: Cash | B8: ='Cash Flow'!B13 -> 216230 | C8: ='Cash Flow'!C13 -> 223325 | D8: ='Cash Flow'!D13 -> 237815
A9: Total assets | B9: =SUM(B5:B8) -> 19191230 | C9: =SUM(C5:C8) -> 19173325 | D9: =SUM(D5:D8) -> 19162815
A11: Mortgage debt | B11: =Assumptions!$B$8-Assumptions!$B$9 -> 9966000 | C11: =Assumptions!$B$8-Assumptions!$B$9*2 -> 9932000 | D11: =Assumptions!$B$8-Assumptions!$B$9*3 -> 9898000
A12: Owner’s equity | B12: =B9-B11 -> 9225230 | C12: =C9-C11 -> 9241325 | D12: =D9-D11 -> 9264815
A13: Total liabilities and equity | B13: =B11+B12 -> 19191230 | C13: =C11+C12 -> 19173325 | D13: =D11+D12 -> 19162815
A14: Check: Assets - Liabilities & Equity | B14: =B9-B13 -> 0 | C14: =C9-C13 -> 0 | D14: =D9-D13 -> 0
A17: Teaching note: the Balance Sheet connects P&L and Cash Flow through assets, debt, cash, and equity.

Sheet Cash Flow
A1: Cash Flow Statement
A2: Monthly cash movement
A4: Cash Flow item | B4: January | C4: February | D4: March
A5: Cash received from tenant | B5: =Assumptions!$B$12 -> 80000 | C5: =Assumptions!$B$12 -> 80000 | D5: =Assumptions!$B$12 -> 80000
A6: Utilities paid | B6: -6000 | C6: -6500 | D6: -6000
A7: Maintenance and repairs paid | B7: -5000 | C7: -15000 | D7: -7000
A8: Mortgage interest paid | B8: =-Assumptions!$B$10 -> -15000 | C8: =-Assumptions!$B$10 -> -15000 | D8: =-Assumptions!$B$10 -> -15000
A9: Mortgage principal repaid | B9: =-Assumptions!$B$9 -> -34000 | C9: =-Assumptions!$B$9 -> -34000 | D9: =-Assumptions!$B$9 -> -34000
A10: Income tax paid | B10: ='P&L'!B11 -> -3770 | C10: ='P&L'!C11 -> -2405 | D10: ='P&L'!D11 -> -3510
A11: Net cash flow for the month | B11: =SUM(B5:B10) -> 16230 | C11: =SUM(C5:C10) -> 7095 | D11: =SUM(D5:D10) -> 14490
A12: Cash balance at the beginning of the month | B12: =Assumptions!$B$11 -> 200000 | C12: =B13 -> 216230 | D12: =C13 -> 223325
A13: Cash balance at the end of the month | B13: =B11+B12 -> 216230 | C13: =C11+C12 -> 223325 | D13: =D11+D12 -> 237815
A16: Teaching note: tax is both an expense in P&L and a cash outflow in Cash Flow. Depreciation of renovation and furniture/appliances is not a monthly cash outflow here. The 49,000 mortgage payment is split into interest and principal; only interest is an expense in P&L.

Sheet Ratios
A1: Ratios
A4: Building blocks (quarter)
A5: Rental revenue | B5: =SUM('P&L'!B5:D5) -> 240000
A6: Operating cash costs | B6: =SUM('P&L'!B6:D7) -> -45500
A7: Mortgage interest | B7: =SUM('P&L'!B8:D8) -> -45000
A8: Depreciation | B8: =SUM('P&L'!B9:D9) -> -75000
A9: Profit before tax | B9: =SUM('P&L'!B10:D10) -> 74500
A10: Income tax | B10: =SUM('P&L'!B11:D11) -> -9685
A11: Net profit | B11: =SUM('P&L'!B12:D12) -> 64815
A12: Operating net cash flow | B12: =SUM('Cash Flow'!B11:D11) -> 37815
A13: Total assets (end Mar) | B13: ='Balance Sheet'!D9 -> 19162815
A14: Owners equity (end Mar) | B14: ='Balance Sheet'!D12 -> 9264815
A15: Mortgage debt (end Mar) | B15: ='Balance Sheet'!D11 -> 9898000
A16: Cash (end Mar) | B16: ='Balance Sheet'!D8 -> 237815
A17: Asset base (price proxy) | B17: =Assumptions!$B$4+Assumptions!$B$5+Assumptions!$B$6 -> 19000000
A19: EBITDA = revenue minus operating cash costs (before interest tax depreciation)
A20: EBITDA | B20: =$B$5+$B$6 -> 194500
A22: Ratio | B22: Formula (plain) | C22: Value
A23: P/E | B23: Asset price / annual net profit | C23: =$B$17/($B$11*4) -> 73.285505
A24: ROA | B24: Annual net profit / total assets | C24: =($B$11*4)/$B$13 -> 0.013529328
A25: ROE | B25: Annual net profit / owner equity | C25: =($B$11*4)/$B$14 -> 0.027983289
A26: Net Profit Margin | B26: Net profit / revenue | C26: =$B$11/$B$5 -> 0.2700625
A27: Gross Margin | B27: (Revenue minus direct operating costs) / revenue | C27: =($B$5+$B$6)/$B$5 -> 0.81041667
A28: EBITDA | B28: Revenue minus operating cash costs | C28: =$B$20 -> 194500
A29: EBITDA Margin | B29: EBITDA / revenue | C29: =$B$20/$B$5 -> 0.81041667
A30: Net Debt / EBITDA | B30: (Mortgage minus cash) / annual EBITDA | C30: =($B$15-$B$16)/($B$20*4) -> 12.41669
A31: EV / EBITDA | B31: (Asset price plus net debt) / annual EBITDA | C31: =($B$17+$B$15-$B$16)/($B$20*4) -> 36.838284
A32: Cash Conversion | B32: Operating net cash flow / EBITDA | C32: =$B$12/$B$20 -> 0.19442159
